odoo/addons/vh_invoicing/__init__.py
odoo/addons/vh_invoicing/__manifest__.py
odoo/addons/vh_invoicing/config/__init__.py
odoo/addons/vh_invoicing/config/vh_company.py
odoo/addons/vh_invoicing/config/vh_invoicing_config_settings.py
odoo/addons/vh_invoicing/data/vh_account_journal.xml
odoo/addons/vh_invoicing/data/vh_ir_sequence.xml
odoo/addons/vh_invoicing/models/__init__.py
odoo/addons/vh_invoicing/models/vh_abstract_contract.py
odoo/addons/vh_invoicing/models/vh_account_invoice.py
odoo/addons/vh_invoicing/models/vh_account_journal.py
odoo/addons/vh_invoicing/models/vh_company.py
odoo/addons/vh_invoicing/models/vh_config_settings.py
odoo/addons/vh_invoicing/models/vh_contract.py
odoo/addons/vh_invoicing/models/vh_invoicing_contact_group.py
odoo/addons/vh_invoicing/models/vh_invoicing_order.py
odoo/addons/vh_invoicing/models/vh_invoicing_order_item.py
odoo/addons/vh_invoicing/models/vh_model_sequence_mixin.py
odoo/addons/vh_invoicing/models/vh_partner.py
odoo/addons/vh_invoicing/security/ir.model.access.csv
odoo/addons/vh_invoicing/views/report_vh_invoicing_order_item.xml
odoo/addons/vh_invoicing/views/vh_account_journal.xml
odoo/addons/vh_invoicing/views/vh_config_settings.xml
odoo/addons/vh_invoicing/views/vh_contract.xml
odoo/addons/vh_invoicing/views/vh_contract_template.xml
odoo/addons/vh_invoicing/views/vh_invoice.xml
odoo/addons/vh_invoicing/views/vh_invoicing_contact_group.xml
odoo/addons/vh_invoicing/views/vh_invoicing_menu_root_config.xml
odoo/addons/vh_invoicing/views/vh_invoicing_order.xml
odoo/addons/vh_invoicing/views/vh_invoicing_order_item.xml
odoo/addons/vh_invoicing/views/vh_invoicing_order_item_email.xml
odoo/addons/vh_invoicing/views/vh_payment_order.xml
odoo/addons/vh_invoicing/views/vh_product.xml
odoo12_addon_vh_invoicing-12.0.0.1.5.dist-info/METADATA
odoo12_addon_vh_invoicing-12.0.0.1.5.dist-info/WHEEL
odoo12_addon_vh_invoicing-12.0.0.1.5.dist-info/top_level.txt
odoo12_addon_vh_invoicing-12.0.0.1.5.dist-info/RECORD
