Metadata-Version: 2.1
Name: odoo12-addon-vh-invoicing
Version: 12.0.0.1.5
Summary: Invoicing process for habitatge.
Home-page: https://gitlab.com/coopdevs/vertical-habitatge
Author: Coopdevs
License: UNKNOWN
Platform: UNKNOWN
Classifier: Programming Language :: Python
Classifier: Framework :: Odoo
Classifier: Framework :: Odoo :: 12.0
Requires-Python: >=3.5
Requires-Dist: odoo12-addon-account-payment-mode
Requires-Dist: odoo12-addon-account-payment-order
Requires-Dist: odoo12-addon-contract
Requires-Dist: odoo12-addon-vh
Requires-Dist: odoo (<12.1dev,>=12.0a)
